[
    {
        "id": 1,
        "title": "My Mission",
        "logo": "M",
        "text": "I like programming very much. I don't see it as a profession, it's my real addiction. Programming is my passion. My first mission is to establish myself in web development."
    },
    {
        "id": 2,
        "title": "My Vision",
        "logo": "V",
        "text": "Within the next two years I started working in this field with the conviction of making a good position in programming. vision is to satisfy the client and collect positive reviews."
    },
    {
        "id": 3,
        "title": "My Ambition",
        "logo": "A",
        "text": "My ambition is to build a good career in problem solving. I know that the better the problem, the better the programmer. My only attempt is to be a good programmer."
    }
]